pyconversations/__init__.py
pyconversations/__main__.py
pyconversations/cli.py
pyconversations/convo.py
pyconversations/feature_extraction/__init__.py
pyconversations/feature_extraction/conv.py
pyconversations/feature_extraction/extractors.py
pyconversations/feature_extraction/harmonic.py
pyconversations/feature_extraction/params.py
pyconversations/feature_extraction/post.py
pyconversations/feature_extraction/post_in_conv.py
pyconversations/feature_extraction/regex.py
pyconversations/feature_extraction/user_across_conv.py
pyconversations/feature_extraction/user_in_conv.py
pyconversations/ld/__init__.py
pyconversations/ld/base.py
pyconversations/ld/lid.py
pyconversations/message/__init__.py
pyconversations/message/base.py
pyconversations/message/chan.py
pyconversations/message/facebook.py
pyconversations/message/reddit.py
pyconversations/message/twitter.py
pyconversations/reader/__init__.py
pyconversations/reader/base.py
pyconversations/reader/chan.py
pyconversations/reader/facebook.py
pyconversations/reader/reddit.py
pyconversations/reader/twitter.py
pyconversations/tokenizers/__init__.py
pyconversations/tokenizers/base.py
pyconversations/tokenizers/chars.txt
pyconversations/tokenizers/default.py
pyconversations/tokenizers/nltk.py
pyconversations/tokenizers/partitioner.py
pyconversations/tokenizers/wrapper.py
pyconversations-0.1.0.dist-info/AUTHORS.rst
pyconversations-0.1.0.dist-info/LICENSE
pyconversations-0.1.0.dist-info/METADATA
pyconversations-0.1.0.dist-info/WHEEL
pyconversations-0.1.0.dist-info/entry_points.txt
pyconversations-0.1.0.dist-info/top_level.txt
pyconversations-0.1.0.dist-info/RECORD
