Metadata-Version: 2.1
Name: pyconversations
Version: 0.1.0
Summary: A package for representing conversations as DAGs for visualization, analysis, and pre-processing.
Home-page: https://github.com/hunter-heidenreich/pyconversations
Author: Hunter Scott Heidenreich
Author-email: hunter.scott.heidenreich@gmail.com
License: MIT
Project-URL: Documentation, https://pyconversations.readthedocs.io/
Project-URL: Changelog, https://pyconversations.readthedocs.io/en/latest/changelog.html
Project-URL: Issue Tracker, https://github.com/hunter-heidenreich/pyconversations/issues
Platform: UNKNOWN
Classifier: Development Status :: 5 - Production/Stable
Classifier: Intended Audience :: Developers
Classifier: License :: OSI Approved :: MIT License
Classifier: Operating System :: Unix
Classifier: Operating System :: POSIX
Classifier: Operating System :: Microsoft :: Windows
Classifier: Programming Language :: Python
Classifier: Programming Language :: Python :: 3
Classifier: Programming Language :: Python :: 3 :: Only
Classifier: Programming Language :: Python :: 3.6
Classifier: Programming Language :: Python :: 3.7
Classifier: Topic :: Utilities
Requires-Python: >=3.6
License-File: LICENSE
License-File: AUTHORS.rst
Requires-Dist: networkx (>=2.5)
Requires-Dist: langid (>=1.1)
Requires-Dist: numpy (>=1.12)
Requires-Dist: tqdm (>=4.59)
Requires-Dist: nltk (>=3.0)
Requires-Dist: demoji (>=1.0)
Requires-Dist: scipy (>=1.7.0)
